dockerctx.py
dockerctx-2024.3.2.dist-info/LICENSE
dockerctx-2024.3.2.dist-info/WHEEL
dockerctx-2024.3.2.dist-info/METADATA
dockerctx-2024.3.2.dist-info/RECORD
