Metadata-Version: 2.1
Name: dockerctx
Version: 2024.3.2
Summary: A context manager for a docker container. 
Home-page: https://github.com/cjrh/dockerctx
Author: Caleb Hattingh
Author-email: caleb.hattingh@gmail.com
Classifier: License :: OSI Approved :: MIT License
Classifier: Intended Audience :: Developers
Classifier: Natural Language :: English
Classifier: Programming Language :: Python
Classifier: Programming Language :: Python :: 3.7
Classifier: Programming Language :: Python :: 3.8
Classifier: Programming Language :: Python :: 3.9
Classifier: Programming Language :: Python :: 3.10
Classifier: Programming Language :: Python :: 3.11
Classifier: Programming Language :: Python :: 3.12
Classifier: Topic :: Software Development :: Libraries :: Python Modules
Requires-Dist: docker
Requires-Dist: typing; python_version < '3.5'
Requires-Dist: psycopg2-binary
Requires-Dist: sqlalchemy ; extra == "dev"
Requires-Dist: sqlalchemy_utils ; extra == "dev"
Requires-Dist: sqllogformatter ; extra == "dev"
Requires-Dist: pytest ; extra == "dev"
Requires-Dist: redis ; extra == "dev"
Provides-Extra: dev
